{
	"name": "Load ERP Felipe",
	"properties": {
		"activities": [
			{
				"name": "LOAD CATEGORIA",
				"type": "Copy",
				"dependsOn": [],
				"policy": {
					"timeout": "0.12:00:00",
					"retry": 0,
					"retryIntervalInSeconds": 30,
					"secureOutput": false,
					"secureInput": false
				},
				"userProperties": [],
				"typeProperties": {
					"source": {
						"type": "SqlServerSource",
						"queryTimeout": "02:00:00",
						"partitionOption": "None"
					},
					"sink": {
						"type": "ParquetSink",
						"storeSettings": {
							"type": "AzureBlobFSWriteSettings"
						},
						"formatSettings": {
							"type": "ParquetWriteSettings"
						}
					},
					"enableStaging": false,
					"translator": {
						"type": "TabularTranslator",
						"mappings": [
							{
								"source": {
									"name": "ID_CATEGORIA",
									"type": "Int32",
									"physicalType": "int"
								},
								"sink": {
									"name": "ID_CATEGORIA",
									"type": "Int32",
									"physicalType": "INT_32"
								}
							},
							{
								"source": {
									"name": "NOME_CATEGORIA",
									"type": "String",
									"physicalType": "varchar"
								},
								"sink": {
									"name": "NOME_CATEGORIA",
									"type": "String",
									"physicalType": "UTF8"
								}
							}
						],
						"typeConversion": true,
						"typeConversionSettings": {
							"allowDataTruncation": true,
							"treatBooleanAsNumber": false
						}
					}
				},
				"inputs": [
					{
						"referenceName": "TB_CATEGORIA_FELIPE",
						"type": "DatasetReference"
					}
				],
				"outputs": [
					{
						"referenceName": "PQ_CATEGORIA_FELIPE",
						"type": "DatasetReference"
					}
				]
			},
			{
				"name": "LOAD CIDADE",
				"type": "Copy",
				"dependsOn": [
					{
						"activity": "LOAD CATEGORIA",
						"dependencyConditions": [
							"Succeeded"
						]
					}
				],
				"policy": {
					"timeout": "0.12:00:00",
					"retry": 0,
					"retryIntervalInSeconds": 30,
					"secureOutput": false,
					"secureInput": false
				},
				"userProperties": [],
				"typeProperties": {
					"source": {
						"type": "SqlServerSource",
						"queryTimeout": "02:00:00",
						"partitionOption": "None"
					},
					"sink": {
						"type": "ParquetSink",
						"storeSettings": {
							"type": "AzureBlobFSWriteSettings"
						},
						"formatSettings": {
							"type": "ParquetWriteSettings"
						}
					},
					"enableStaging": false,
					"translator": {
						"type": "TabularTranslator",
						"mappings": [
							{
								"source": {
									"name": "ID_CATEGORIA",
									"type": "Int32",
									"physicalType": "int"
								},
								"sink": {
									"name": "ID_CATEGORIA",
									"type": "Int32",
									"physicalType": "INT_32"
								}
							},
							{
								"source": {
									"name": "NOME_CATEGORIA",
									"type": "String",
									"physicalType": "varchar"
								},
								"sink": {
									"name": "NOME_CATEGORIA",
									"type": "String",
									"physicalType": "UTF8"
								}
							}
						],
						"typeConversion": true,
						"typeConversionSettings": {
							"allowDataTruncation": true,
							"treatBooleanAsNumber": false
						}
					}
				},
				"inputs": [
					{
						"referenceName": "TBL_CIDADE_FELIPE",
						"type": "DatasetReference"
					}
				],
				"outputs": [
					{
						"referenceName": "PQ_CIDADE_FELIPE",
						"type": "DatasetReference"
					}
				]
			},
			{
				"name": "LOAD CLIENTE",
				"type": "Copy",
				"dependsOn": [
					{
						"activity": "LOAD CIDADE",
						"dependencyConditions": [
							"Succeeded"
						]
					}
				],
				"policy": {
					"timeout": "0.12:00:00",
					"retry": 0,
					"retryIntervalInSeconds": 30,
					"secureOutput": false,
					"secureInput": false
				},
				"userProperties": [],
				"typeProperties": {
					"source": {
						"type": "SqlServerSource",
						"queryTimeout": "02:00:00",
						"partitionOption": "None"
					},
					"sink": {
						"type": "ParquetSink",
						"storeSettings": {
							"type": "AzureBlobFSWriteSettings"
						},
						"formatSettings": {
							"type": "ParquetWriteSettings"
						}
					},
					"enableStaging": false,
					"translator": {
						"type": "TabularTranslator",
						"mappings": [
							{
								"source": {
									"name": "ID_CATEGORIA",
									"type": "Int32",
									"physicalType": "int"
								},
								"sink": {
									"name": "ID_CATEGORIA",
									"type": "Int32",
									"physicalType": "INT_32"
								}
							},
							{
								"source": {
									"name": "NOME_CATEGORIA",
									"type": "String",
									"physicalType": "varchar"
								},
								"sink": {
									"name": "NOME_CATEGORIA",
									"type": "String",
									"physicalType": "UTF8"
								}
							}
						],
						"typeConversion": true,
						"typeConversionSettings": {
							"allowDataTruncation": true,
							"treatBooleanAsNumber": false
						}
					}
				},
				"inputs": [
					{
						"referenceName": "TBL_CLIENTE_FELIPE",
						"type": "DatasetReference"
					}
				],
				"outputs": [
					{
						"referenceName": "PQ_CLIENTE_FELIPE",
						"type": "DatasetReference"
					}
				]
			},
			{
				"name": "LOAD PRODUTOS",
				"type": "Copy",
				"dependsOn": [
					{
						"activity": "LOAD CLIENTE",
						"dependencyConditions": [
							"Succeeded"
						]
					}
				],
				"policy": {
					"timeout": "0.12:00:00",
					"retry": 0,
					"retryIntervalInSeconds": 30,
					"secureOutput": false,
					"secureInput": false
				},
				"userProperties": [],
				"typeProperties": {
					"source": {
						"type": "SqlServerSource",
						"queryTimeout": "02:00:00",
						"partitionOption": "None"
					},
					"sink": {
						"type": "ParquetSink",
						"storeSettings": {
							"type": "AzureBlobFSWriteSettings"
						},
						"formatSettings": {
							"type": "ParquetWriteSettings"
						}
					},
					"enableStaging": false,
					"translator": {
						"type": "TabularTranslator",
						"mappings": [
							{
								"source": {
									"name": "ID_CATEGORIA",
									"type": "Int32",
									"physicalType": "int"
								},
								"sink": {
									"name": "ID_CATEGORIA",
									"type": "Int32",
									"physicalType": "INT_32"
								}
							},
							{
								"source": {
									"name": "NOME_CATEGORIA",
									"type": "String",
									"physicalType": "varchar"
								},
								"sink": {
									"name": "NOME_CATEGORIA",
									"type": "String",
									"physicalType": "UTF8"
								}
							}
						],
						"typeConversion": true,
						"typeConversionSettings": {
							"allowDataTruncation": true,
							"treatBooleanAsNumber": false
						}
					}
				},
				"inputs": [
					{
						"referenceName": "TBL_PRODUTOS_FELIPE",
						"type": "DatasetReference"
					}
				],
				"outputs": [
					{
						"referenceName": "PQ_PRODUTOS_FELIPE",
						"type": "DatasetReference"
					}
				]
			},
			{
				"name": "LOAD UNIDADE",
				"type": "Copy",
				"dependsOn": [
					{
						"activity": "LOAD PRODUTOS",
						"dependencyConditions": [
							"Succeeded"
						]
					}
				],
				"policy": {
					"timeout": "0.12:00:00",
					"retry": 0,
					"retryIntervalInSeconds": 30,
					"secureOutput": false,
					"secureInput": false
				},
				"userProperties": [],
				"typeProperties": {
					"source": {
						"type": "SqlServerSource",
						"queryTimeout": "02:00:00",
						"partitionOption": "None"
					},
					"sink": {
						"type": "ParquetSink",
						"storeSettings": {
							"type": "AzureBlobFSWriteSettings"
						},
						"formatSettings": {
							"type": "ParquetWriteSettings"
						}
					},
					"enableStaging": false,
					"translator": {
						"type": "TabularTranslator",
						"mappings": [
							{
								"source": {
									"name": "ID_CATEGORIA",
									"type": "Int32",
									"physicalType": "int"
								},
								"sink": {
									"name": "ID_CATEGORIA",
									"type": "Int32",
									"physicalType": "INT_32"
								}
							},
							{
								"source": {
									"name": "NOME_CATEGORIA",
									"type": "String",
									"physicalType": "varchar"
								},
								"sink": {
									"name": "NOME_CATEGORIA",
									"type": "String",
									"physicalType": "UTF8"
								}
							}
						],
						"typeConversion": true,
						"typeConversionSettings": {
							"allowDataTruncation": true,
							"treatBooleanAsNumber": false
						}
					}
				},
				"inputs": [
					{
						"referenceName": "TBL_UNIDADE_FELIPE",
						"type": "DatasetReference"
					}
				],
				"outputs": [
					{
						"referenceName": "PQ_UNIDADE_FELIPE",
						"type": "DatasetReference"
					}
				]
			},
			{
				"name": "LOAD VENDAS",
				"type": "Copy",
				"dependsOn": [
					{
						"activity": "LOAD UNIDADE",
						"dependencyConditions": [
							"Succeeded"
						]
					}
				],
				"policy": {
					"timeout": "0.12:00:00",
					"retry": 0,
					"retryIntervalInSeconds": 30,
					"secureOutput": false,
					"secureInput": false
				},
				"userProperties": [],
				"typeProperties": {
					"source": {
						"type": "SqlServerSource",
						"queryTimeout": "02:00:00",
						"partitionOption": "None"
					},
					"sink": {
						"type": "ParquetSink",
						"storeSettings": {
							"type": "AzureBlobFSWriteSettings"
						},
						"formatSettings": {
							"type": "ParquetWriteSettings"
						}
					},
					"enableStaging": false,
					"translator": {
						"type": "TabularTranslator",
						"mappings": [
							{
								"source": {
									"name": "ID_CATEGORIA",
									"type": "Int32",
									"physicalType": "int"
								},
								"sink": {
									"name": "ID_CATEGORIA",
									"type": "Int32",
									"physicalType": "INT_32"
								}
							},
							{
								"source": {
									"name": "NOME_CATEGORIA",
									"type": "String",
									"physicalType": "varchar"
								},
								"sink": {
									"name": "NOME_CATEGORIA",
									"type": "String",
									"physicalType": "UTF8"
								}
							}
						],
						"typeConversion": true,
						"typeConversionSettings": {
							"allowDataTruncation": true,
							"treatBooleanAsNumber": false
						}
					}
				},
				"inputs": [
					{
						"referenceName": "TBL_VENDAS_FELIPE",
						"type": "DatasetReference"
					}
				],
				"outputs": [
					{
						"referenceName": "PQ_VENDAS_FELIPE",
						"type": "DatasetReference"
					}
				]
			},
			{
				"name": "LOAD VENDAS_ITENS",
				"type": "Copy",
				"dependsOn": [
					{
						"activity": "LOAD VENDAS",
						"dependencyConditions": [
							"Succeeded"
						]
					}
				],
				"policy": {
					"timeout": "0.12:00:00",
					"retry": 0,
					"retryIntervalInSeconds": 30,
					"secureOutput": false,
					"secureInput": false
				},
				"userProperties": [],
				"typeProperties": {
					"source": {
						"type": "SqlServerSource",
						"queryTimeout": "02:00:00",
						"partitionOption": "None"
					},
					"sink": {
						"type": "ParquetSink",
						"storeSettings": {
							"type": "AzureBlobFSWriteSettings"
						},
						"formatSettings": {
							"type": "ParquetWriteSettings"
						}
					},
					"enableStaging": false,
					"translator": {
						"type": "TabularTranslator",
						"mappings": [
							{
								"source": {
									"name": "ID_CATEGORIA",
									"type": "Int32",
									"physicalType": "int"
								},
								"sink": {
									"name": "ID_CATEGORIA",
									"type": "Int32",
									"physicalType": "INT_32"
								}
							},
							{
								"source": {
									"name": "NOME_CATEGORIA",
									"type": "String",
									"physicalType": "varchar"
								},
								"sink": {
									"name": "NOME_CATEGORIA",
									"type": "String",
									"physicalType": "UTF8"
								}
							}
						],
						"typeConversion": true,
						"typeConversionSettings": {
							"allowDataTruncation": true,
							"treatBooleanAsNumber": false
						}
					}
				},
				"inputs": [
					{
						"referenceName": "TBL_VENDAS_ITENS_FELIPE",
						"type": "DatasetReference"
					}
				],
				"outputs": [
					{
						"referenceName": "PQ_VENDAS_ITENS_FELIPE",
						"type": "DatasetReference"
					}
				]
			},
			{
				"name": "LOAD VENDEDORES",
				"type": "Copy",
				"dependsOn": [
					{
						"activity": "LOAD VENDAS_ITENS",
						"dependencyConditions": [
							"Succeeded"
						]
					}
				],
				"policy": {
					"timeout": "0.12:00:00",
					"retry": 0,
					"retryIntervalInSeconds": 30,
					"secureOutput": false,
					"secureInput": false
				},
				"userProperties": [],
				"typeProperties": {
					"source": {
						"type": "SqlServerSource",
						"queryTimeout": "02:00:00",
						"partitionOption": "None"
					},
					"sink": {
						"type": "ParquetSink",
						"storeSettings": {
							"type": "AzureBlobFSWriteSettings"
						},
						"formatSettings": {
							"type": "ParquetWriteSettings"
						}
					},
					"enableStaging": false,
					"translator": {
						"type": "TabularTranslator",
						"mappings": [
							{
								"source": {
									"name": "ID_CATEGORIA",
									"type": "Int32",
									"physicalType": "int"
								},
								"sink": {
									"name": "ID_CATEGORIA",
									"type": "Int32",
									"physicalType": "INT_32"
								}
							},
							{
								"source": {
									"name": "NOME_CATEGORIA",
									"type": "String",
									"physicalType": "varchar"
								},
								"sink": {
									"name": "NOME_CATEGORIA",
									"type": "String",
									"physicalType": "UTF8"
								}
							}
						],
						"typeConversion": true,
						"typeConversionSettings": {
							"allowDataTruncation": true,
							"treatBooleanAsNumber": false
						}
					}
				},
				"inputs": [
					{
						"referenceName": "SqlServerTable2",
						"type": "DatasetReference"
					}
				],
				"outputs": [
					{
						"referenceName": "PQ_VENDEDORES_FELIPE",
						"type": "DatasetReference"
					}
				]
			}
		],
		"folder": {
			"name": "Felipe"
		},
		"annotations": [],
		"lastPublishTime": "2022-12-28T12:53:51Z"
	},
	"type": "Microsoft.Synapse/workspaces/pipelines"
}